arasmas/__init__.py
arasmas/__version__.py
arasmas/_main_.py
arasmas/MD/__init__.py
arasmas/MD/dataclass.py
arasmas/MD/generator.py
arasmas/MD/interface.py
arasmas/MD/main.py
arasmas/MD/program/__init__.py
arasmas/MD/program/lammps.py
arasmas/MD/to_qm/__init__.py
arasmas/MD/to_qm/evaluator_force.py
arasmas/MD/to_qm/interface.py
arasmas/MD/to_qm/standard.py
arasmas/cli/__init__.py
arasmas/cli/run.py
arasmas/ff/__init__.py
arasmas/ff/dataclass.py
arasmas/ff/generator.py
arasmas/ff/interface.py
arasmas/ff/program/__init__.py
arasmas/ff/program/allegro.py
arasmas/ff/program/dpmd.py
arasmas/ff/to_md/__init__.py
arasmas/ff/to_md/allegro.py
arasmas/ff/to_md/deepmd.py
arasmas/ff/to_md/interface.py
arasmas/tools/__init__.py
arasmas/tools/atom.py
arasmas/tools/yaml.py
arasmas-0.0.1.dist-info/LICENSE
arasmas-0.0.1.dist-info/METADATA
arasmas-0.0.1.dist-info/WHEEL
arasmas-0.0.1.dist-info/top_level.txt
arasmas-0.0.1.dist-info/RECORD
